weather_query/__init__.py
weather_query/client.py
weather_query/preprocess.py
weather_query/setting.py
weather_query_test-0.0.1.dist-info/LICENSE
weather_query_test-0.0.1.dist-info/METADATA
weather_query_test-0.0.1.dist-info/WHEEL
weather_query_test-0.0.1.dist-info/top_level.txt
weather_query_test-0.0.1.dist-info/RECORD
