Metadata-Version: 2.1
Name: weather-query-test
Version: 0.0.1
Summary: forecast weather
Home-page: UNKNOWN
Author: Wook Lee
Author-email: leewook94@gmail.com
License: UNKNOWN
Keywords: api,weather,forecast
Platform: UNKNOWN
Classifier: Programming Language :: Python :: 3
Classifier: License :: OSI Approved :: Apache Software License
Classifier: Operating System :: OS Independent
Requires-Dist: googletrans (==4.0.0rc1)
Requires-Dist: python-dotenv (>=1.0.1)
Requires-Dist: python-multipart (>=0.0.12)
Requires-Dist: requests (>=2.32.3)
